LICENSE
simple_sqlite3/__init__.py
simple_sqlite3/cli.py
simple_sqlite3/database.py
simple_sqlite3/exceptions.py
simple_sqlite3/table.py
simple_sqlite3/utils.py
simple_sqlite3-0.0.10.dist-info/METADATA
simple_sqlite3-0.0.10.dist-info/WHEEL
simple_sqlite3-0.0.10.dist-info/entry_points.txt
simple_sqlite3-0.0.10.dist-info/licenses/LICENSE
simple_sqlite3-0.0.10.dist-info/RECORD
