Metadata-Version: 2.4
Name: simple-sqlite3
Version: 0.0.10
Summary: A simple SQLite3 wrapper for Python
Author-email: Rob Suomi <robert.suomi@gmail.com>
License-Expression: MIT
License-File: LICENSE
Requires-Python: >=3.9
